databusclient/__init__.py
databusclient/__main__.py
databusclient/cli.py
databusclient/client.py
databusclient-0.12.dist-info/METADATA
databusclient-0.12.dist-info/WHEEL
databusclient-0.12.dist-info/RECORD
