Metadata-Version: 2.1
Name: databusclient
Version: 0.12
Summary: A simple client for submitting data to the DBpedia Databus
License: Apache-2.0 License
Author: DBpedia Association
Requires-Python: >=3.9,<4.0
Classifier: License :: Other/Proprietary License
Classifier: Programming Language :: Python :: 3
Classifier: Programming Language :: Python :: 3.9
Classifier: Programming Language :: Python :: 3.10
Classifier: Programming Language :: Python :: 3.11
Requires-Dist: requests (>=2.28.1,<3.0.0)
Requires-Dist: typer (>=0.6.1,<0.7.0)
